<?xml version='1.0' encoding='utf-8'?>
<cfdi:Comprobante xmlns:cfdi="http://www.sat.gob.mx/cfd/4" Version="4.0" Folio="CRP-3" Fecha="2026-05-08T00:00:00" Total="5000.0" SubTotal="4310.34" Moneda="MXN" TipoDeComprobante="P" MetodoPago="PUE" LugarExpedicion="10000"><cfdi:CfdiRelacionados TipoRelacion="04"><cfdi:CfdiRelacionado UUID="F914C9E5-0165-496F-BFA9-C83B9068F4DA" /></cfdi:CfdiRelacionados><cfdi:Emisor Rfc="DEMO123456XYZ" Nombre="EMPRESA DEMO SA DE CV" RegimenFiscal="601" /><cfdi:Receptor Rfc="CLI003" Nombre="CLIENTE PPD" UsoCFDI="G03" RegimenFiscalReceptor="601" DomicilioFiscalReceptor="20000" /><cfdi:Conceptos><cfdi:Concepto ClaveProdServ="84111506" Cantidad="1" ClaveUnidad="E48" Descripcion="Estrategia de marketing digital" ValorUnitario="4310.34" Importe="4310.34" ObjetoImp="02" /></cfdi:Conceptos><cfdi:Complemento><tfd:TimbreFiscalDigital xmlns:tfd="http://www.sat.gob.mx/TimbreFiscalDigital" UUID="7985F1C4-AB77-4F38-9E53-224351D285F7" /></cfdi:Complemento></cfdi:Comprobante>