<?xml version='1.0' encoding='utf-8'?>
<cfdi:Comprobante xmlns:cfdi="http://www.sat.gob.mx/cfd/4" Version="4.0" Folio="V-PARC-0" Fecha="2026-04-05T12:21:21" Total="10000.0" SubTotal="8620.69" Moneda="MXN" TipoDeComprobante="I" MetodoPago="PUE" LugarExpedicion="10000"><cfdi:Emisor Rfc="DEMO123456XYZ" Nombre="EMPRESA DEMO SA DE CV" RegimenFiscal="601" /><cfdi:Receptor Rfc="CLI002" Nombre="CLIENTE PARCIAL" UsoCFDI="G03" RegimenFiscalReceptor="601" DomicilioFiscalReceptor="20000" /><cfdi:Conceptos><cfdi:Concepto ClaveProdServ="84111506" Cantidad="1" ClaveUnidad="E48" Descripcion="Soporte técnico de infraestructura" ValorUnitario="8620.69" Importe="8620.69" ObjetoImp="02" /></cfdi:Conceptos><cfdi:Complemento><tfd:TimbreFiscalDigital xmlns:tfd="http://www.sat.gob.mx/TimbreFiscalDigital" UUID="24EC5FAD-3E2D-4937-B792-D1520DC180DC" /></cfdi:Complemento></cfdi:Comprobante>