<?xml version='1.0' encoding='utf-8'?>
<cfdi:Comprobante xmlns:cfdi="http://www.sat.gob.mx/cfd/4" Version="4.0" Folio="V-PERF-17" Fecha="2026-05-16T05:12:22" Total="1580.2" SubTotal="1362.24" Moneda="MXN" TipoDeComprobante="I" MetodoPago="PUE" LugarExpedicion="10000"><cfdi:Emisor Rfc="DEMO123456XYZ" Nombre="EMPRESA DEMO SA DE CV" RegimenFiscal="601" /><cfdi:Receptor Rfc="CLI001" Nombre="CLIENTE OK" UsoCFDI="G03" RegimenFiscalReceptor="601" DomicilioFiscalReceptor="20000" /><cfdi:Conceptos><cfdi:Concepto ClaveProdServ="84111506" Cantidad="1" ClaveUnidad="E48" Descripcion="Servicios Profesionales" ValorUnitario="1362.24" Importe="1362.24" ObjetoImp="02" /></cfdi:Conceptos><cfdi:Complemento><tfd:TimbreFiscalDigital xmlns:tfd="http://www.sat.gob.mx/TimbreFiscalDigital" UUID="353EE3F1-7BDC-4595-A74C-B50F4904650E" /></cfdi:Complemento></cfdi:Comprobante>