<?xml version='1.0' encoding='utf-8'?>
<cfdi:Comprobante xmlns:cfdi="http://www.sat.gob.mx/cfd/4" Version="4.0" Serie="F" Folio="72" Fecha="2026-05-09T00:17:53" Total="21613.85" SubTotal="18632.63" Moneda="MXN" TipoDeComprobante="I" MetodoPago="PUE" FormaPago="03" LugarExpedicion="10000">
	<cfdi:Emisor Rfc="DEMO123456XYZ" Nombre="EMPRESA DEMO SA DE CV" RegimenFiscal="601" />
	<cfdi:Receptor Rfc="REC115981ABC" Nombre="CLIENTE 72 SA DE CV" UsoCFDI="G03" RegimenFiscalReceptor="601" DomicilioFiscalReceptor="20000" />
	<cfdi:Conceptos>
		<cfdi:Concepto ClaveProdServ="84111506" Cantidad="1" ClaveUnidad="E48" Descripcion="Licenciamiento de software empresarial" ValorUnitario="18632.63" Importe="18632.63" ObjetoImp="02" />
	</cfdi:Conceptos>
	<cfdi:Impuestos TotalImpuestosTrasladados="2981.22">
		<cfdi:Traslados>
			<cfdi:Traslado Base="18632.63" Impuesto="002" TipoFactor="Tasa" TasaOCuota="0.160000" Importe="2981.22" />
		</cfdi:Traslados>
	</cfdi:Impuestos>
	<cfdi:Complemento>
		<tfd:TimbreFiscalDigital xmlns:tfd="http://www.sat.gob.mx/TimbreFiscalDigital" UUID="06B6E9A3-B528-4030-B132-1FFC2BCCC8E3" />
	</cfdi:Complemento>
</cfdi:Comprobante>